traffic_controller.v
module traffic_controller(

input clk,
input reset,

input pedestrian,
input emergency,

input veh_NS,
input veh_EW,

output reg [2:0] NS,
output reg [2:0] EW,

output reg WALK,

output reg ERROR,

output reg [3:0] countdown,

output reg [7:0] cars_count,
output reg [7:0] ped_count,
output reg [7:0] emergency_count

);

parameter S0=3'b000;
parameter S1=3'b001;
parameter S2=3'b010;
parameter S3=3'b011;
parameter S4=3'b100;
parameter S5=3'b101;

reg [2:0] state;
reg [3:0] count;


always @(posedge clk or posedge reset)

begin

if(reset)

begin

state<=S0;
count<=0;

cars_count<=0;
ped_count<=0;
emergency_count<=0;

ERROR<=0;

end

else

begin

count<=count+1;


if(emergency)

begin

state<=S5;

count<=0;

emergency_count<=emergency_count+1;

end


else

begin

case(state)

S0:
begin

countdown<=5-count;

if(veh_NS)
cars_count<=cars_count+1;

if(count==5)

begin
state<=S1;
count<=0;
end

end


S1:

begin

countdown<=2-count;

if(count==2)

begin
state<=S2;
count<=0;
end

end


S2:

begin

countdown<=5-count;

if(veh_EW)
cars_count<=cars_count+1;

if(count==5)

begin
state<=S3;
count<=0;
end

end


S3:

begin

countdown<=2-count;

if(count==2)

begin

if(pedestrian)

state<=S4;

else

state<=S0;

count<=0;

end

end


S4:

begin

WALK<=1;

countdown<=4-count;

if(pedestrian)
ped_count<=ped_count+1;

if(count==4)

begin

state<=S0;
count<=0;

end

end


S5:

begin

countdown<=0;

if(!emergency)

begin

state<=S0;
count<=0;

end

end


endcase

end

end

end



always @(*)

begin

WALK=0;

case(state)

S0:
begin
NS=3'b001;
EW=3'b100;
end


S1:
begin
NS=3'b010;
EW=3'b100;
end


S2:
begin
NS=3'b100;
EW=3'b001;
end


S3:
begin
NS=3'b100;
EW=3'b010;
end


S4:
begin
NS=3'b100;
EW=3'b100;
WALK=1;
end


S5:
begin
NS=3'b001;
EW=3'b100;
end


default:
begin
NS=3'b100;
EW=3'b100;
end

endcase


// Safety Check

if(NS==3'b001 && EW==3'b001)

begin

ERROR=1;

NS=3'b100;
EW=3'b100;

end

else

ERROR=0;


end

endmodule

traffic_tb.v
`timescale 1ns/1ps

module traffic_tb();

reg clk;
reg reset;

reg pedestrian;
reg emergency;

reg veh_NS;
reg veh_EW;

wire [2:0] NS;
wire [2:0] EW;

wire WALK;
wire ERROR;

wire [3:0] countdown;

wire [7:0] cars_count;
wire [7:0] ped_count;
wire [7:0] emergency_count;



traffic_controller DUT(

.clk(clk),
.reset(reset),

.pedestrian(pedestrian),
.emergency(emergency),

.veh_NS(veh_NS),
.veh_EW(veh_EW),

.NS(NS),
.EW(EW),

.WALK(WALK),
.ERROR(ERROR),

.countdown(countdown),

.cars_count(cars_count),
.ped_count(ped_count),
.emergency_count(emergency_count)

);


// Clock generation

always #5 clk = ~clk;



// Test sequence

initial
begin

clk = 0;

reset = 1;

pedestrian = 0;
emergency = 0;

veh_NS = 0;
veh_EW = 0;


#20
reset = 0;


// Heavy traffic at NS road

#50
veh_NS = 1;

#60
veh_NS = 0;


// Heavy traffic at EW road

#100
veh_EW = 1;

#60
veh_EW = 0;


// Pedestrian request

#100
pedestrian = 1;

#20
pedestrian = 0;


// Emergency vehicle

#100
emergency = 1;

#50
emergency = 0;


// Finish simulation

#500
$finish;

end



// Generate VCD

initial
begin

$dumpfile("traffic.vcd");

$dumpvars(0,traffic_tb);

end



// Monitor outputs

initial
begin

$monitor(

"Time=%0t State=%d Count=%d NS=%b EW=%b WALK=%b ERROR=%b Cars=%d Ped=%d Emergency=%d",

$time,
DUT.state,
DUT.count,

NS,
EW,

WALK,
ERROR,

cars_count,
ped_count,
emergency_count

);

end

endmodule

traffic.vcd
$date
	Thu Jun 18 23:11:29 2026
$end
$version
	Icarus Verilog
$end
$timescale
	1ps
$end
$scope module traffic_tb $end
$var wire 8 ! ped_count [7:0] $end
$var wire 8 " emergency_count [7:0] $end
$var wire 4 # countdown [3:0] $end
$var wire 8 $ cars_count [7:0] $end
$var wire 1 % WALK $end
$var wire 3 & NS [2:0] $end
$var wire 3 ' EW [2:0] $end
$var wire 1 ( ERROR $end
$var reg 1 ) clk $end
$var reg 1 * emergency $end
$var reg 1 + pedestrian $end
$var reg 1 , reset $end
$var reg 1 - veh_EW $end
$var reg 1 . veh_NS $end
$scope module DUT $end
$var wire 1 ) clk $end
$var wire 1 * emergency $end
$var wire 1 + pedestrian $end
$var wire 1 , reset $end
$var wire 1 - veh_EW $end
$var wire 1 . veh_NS $end
$var reg 1 ( ERROR $end
$var reg 3 / EW [2:0] $end
$var reg 3 0 NS [2:0] $end
$var reg 1 % WALK $end
$var reg 8 1 cars_count [7:0] $end
$var reg 4 2 count [3:0] $end
$var reg 4 3 countdown [3:0] $end
$var reg 8 4 emergency_count [7:0] $end
$var reg 8 5 ped_count [7:0] $end
$var reg 3 6 state [2:0] $end
$upscope $end
$upscope $end
$enddefinitions $end
#0
$dumpvars
b0 6
b0 5
b0 4
bx 3
b0 2
b0 1
b1 0
b100 /
0.
0-
1,
0+
0*
0)
0(
b100 '
b1 &
0%
b0 $
bx #
b0 "
b0 !
$end
#5000
1)
#10000
0)
#15000
1)
#20000
0)
0,
#25000
b101 #
b101 3
b1 2
1)
#30000
0)
#35000
b100 #
b100 3
b10 2
1)
#40000
0)
#45000
b11 #
b11 3
b11 2
1)
#50000
0)
#55000
b10 #
b10 3
b100 2
1)
#60000
0)
#65000
b1 #
b1 3
b101 2
1)
#70000
0)
1.
#75000
b10 &
b10 0
b1 6
b1 $
b1 1
b0 #
b0 3
b0 2
1)
#80000
0)
#85000
b10 #
b10 3
b1 2
1)
#90000
0)
#95000
b1 #
b1 3
b10 2
1)
#100000
0)
#105000
b1 '
b1 /
b100 &
b100 0
b10 6
b0 #
b0 3
b0 2
1)
#110000
0)
#115000
b101 #
b101 3
b1 2
1)
#120000
0)
#125000
b100 #
b100 3
b10 2
1)
#130000
0)
0.
#135000
b11 #
b11 3
b11 2
1)
#140000
0)
#145000
b10 #
b10 3
b100 2
1)
#150000
0)
#155000
b1 #
b1 3
b101 2
1)
#160000
0)
#165000
b10 '
b10 /
b11 6
b0 #
b0 3
b0 2
1)
#170000
0)
#175000
b10 #
b10 3
b1 2
1)
#180000
0)
#185000
b1 #
b1 3
b10 2
1)
#190000
0)
#195000
b100 '
b100 /
b1 &
b1 0
b0 6
b0 #
b0 3
b0 2
1)
#200000
0)
#205000
b101 #
b101 3
b1 2
1)
#210000
0)
#215000
b100 #
b100 3
b10 2
1)
#220000
0)
#225000
b11 #
b11 3
b11 2
1)
#230000
0)
1-
#235000
b10 #
b10 3
b100 2
1)
#240000
0)
#245000
b1 #
b1 3
b101 2
1)
#250000
0)
#255000
b10 &
b10 0
b1 6
b0 #
b0 3
b0 2
1)
#260000
0)
#265000
b10 #
b10 3
b1 2
1)
#270000
0)
#275000
b1 #
b1 3
b10 2
1)
#280000
0)
#285000
b1 '
b1 /
b100 &
b100 0
b10 6
b0 #
b0 3
b0 2
1)
#290000
0)
0-
#295000
b101 #
b101 3
b1 2
1)
#300000
0)
#305000
b100 #
b100 3
b10 2
1)
#310000
0)
#315000
b11 #
b11 3
b11 2
1)
#320000
0)
#325000
b10 #
b10 3
b100 2
1)
#330000
0)
#335000
b1 #
b1 3
b101 2
1)
#340000
0)
#345000
b10 '
b10 /
b11 6
b0 #
b0 3
b0 2
1)
#350000
0)
#355000
b10 #
b10 3
b1 2
1)
#360000
0)
#365000
b1 #
b1 3
b10 2
1)
#370000
0)
#375000
b100 '
b100 /
b1 &
b1 0
b0 6
b0 #
b0 3
b0 2
1)
#380000
0)
#385000
b101 #
b101 3
b1 2
1)
#390000
0)
1+
#395000
b100 #
b100 3
b10 2
1)
#400000
0)
#405000
b11 #
b11 3
b11 2
1)
#410000
0)
0+
#415000
b10 #
b10 3
b100 2
1)
#420000
0)
#425000
b1 #
b1 3
b101 2
1)
#430000
0)
#435000
b10 &
b10 0
b1 6
b0 #
b0 3
b0 2
1)
#440000
0)
#445000
b10 #
b10 3
b1 2
1)
#450000
0)
#455000
b1 #
b1 3
b10 2
1)
#460000
0)
#465000
b1 '
b1 /
b100 &
b100 0
b10 6
b0 #
b0 3
b0 2
1)
#470000
0)
#475000
b101 #
b101 3
b1 2
1)
#480000
0)
#485000
b100 #
b100 3
b10 2
1)
#490000
0)
#495000
b11 #
b11 3
b11 2
1)
#500000
0)
#505000
b10 #
b10 3
b100 2
1)
#510000
0)
1*
#515000
b100 '
b100 /
b1 &
b1 0
b1 "
b1 4
b101 6
b0 2
1)
#520000
0)
#525000
b10 "
b10 4
b0 2
1)
#530000
0)
#535000
b11 "
b11 4
b0 2
1)
#540000
0)
#545000
b100 "
b100 4
b0 2
1)
#550000
0)
#555000
b101 "
b101 4
b0 2
1)
#560000
0)
0*
#565000
b0 6
b0 #
b0 3
b0 2
1)
#570000
0)
#575000
b101 #
b101 3
b1 2
1)
#580000
0)
#585000
b100 #
b100 3
b10 2
1)
#590000
0)
#595000
b11 #
b11 3
b11 2
1)
#600000
0)
#605000
b10 #
b10 3
b100 2
1)
#610000
0)
#615000
b1 #
b1 3
b101 2
1)
#620000
0)
#625000
b10 &
b10 0
b1 6
b0 #
b0 3
b0 2
1)
#630000
0)
#635000
b10 #
b10 3
b1 2
1)
#640000
0)
#645000
b1 #
b1 3
b10 2
1)
#650000
0)
#655000
b1 '
b1 /
b100 &
b100 0
b10 6
b0 #
b0 3
b0 2
1)
#660000
0)
#665000
b101 #
b101 3
b1 2
1)
#670000
0)
#675000
b100 #
b100 3
b10 2
1)
#680000
0)
#685000
b11 #
b11 3
b11 2
1)
#690000
0)
#695000
b10 #
b10 3
b100 2
1)
#700000
0)
#705000
b1 #
b1 3
b101 2
1)
#710000
0)
#715000
b10 '
b10 /
b11 6
b0 #
b0 3
b0 2
1)
#720000
0)
#725000
b10 #
b10 3
b1 2
1)
#730000
0)
#735000
b1 #
b1 3
b10 2
1)
#740000
0)
#745000
b100 '
b100 /
b1 &
b1 0
b0 6
b0 #
b0 3
b0 2
1)
#750000
0)
#755000
b101 #
b101 3
b1 2
1)
#760000
0)
#765000
b100 #
b100 3
b10 2
1)
#770000
0)
#775000
b11 #
b11 3
b11 2
1)
#780000
0)
#785000
b10 #
b10 3
b100 2
1)
#790000
0)
#795000
b1 #
b1 3
b101 2
1)
#800000
0)
#805000
b10 &
b10 0
b1 6
b0 #
b0 3
b0 2
1)
#810000
0)
#815000
b10 #
b10 3
b1 2
1)
#820000
0)
#825000
b1 #
b1 3
b10 2
1)
#830000
0)
#835000
b1 '
b1 /
b100 &
b100 0
b10 6
b0 #
b0 3
b0 2
1)
#840000
0)
#845000
b101 #
b101 3
b1 2
1)
#850000
0)
#855000
b100 #
b100 3
b10 2
1)
#860000
0)
#865000
b11 #
b11 3
b11 2
1)
#870000
0)
#875000
b10 #
b10 3
b100 2
1)
#880000
0)
#885000
b1 #
b1 3
b101 2
1)
#890000
0)
#895000
b10 '
b10 /
b11 6
b0 #
b0 3
b0 2
1)
#900000
0)
#905000
b10 #
b10 3
b1 2
1)
#910000
0)
#915000
b1 #
b1 3
b10 2
1)
#920000
0)
#925000
b100 '
b100 /
b1 &
b1 0
b0 6
b0 #
b0 3
b0 2
1)
#930000
0)
#935000
b101 #
b101 3
b1 2
1)
#940000
0)
#945000
b100 #
b100 3
b10 2
1)
#950000
0)
#955000
b11 #
b11 3
b11 2
1)
#960000
0)
#965000
b10 #
b10 3
b100 2
1)
#970000
0)
#975000
b1 #
b1 3
b101 2
1)
#980000
0)
#985000
b10 &
b10 0
b1 6
b0 #
b0 3
b0 2
1)
#990000
0)
#995000
b10 #
b10 3
b1 2
1)
#1000000
0)
#1005000
b1 #
b1 3
b10 2
1)
#1010000
0)
#1015000
b1 '
b1 /
b100 &
b100 0
b10 6
b0 #
b0 3
b0 2
1)
#1020000
0)
#1025000
b101 #
b101 3
b1 2
1)
#1030000
0)
#1035000
b100 #
b100 3
b10 2
1)
#1040000
0)
#1045000
b11 #
b11 3
b11 2
1)
#1050000
0)
#1055000
b10 #
b10 3
b100 2
1)
